src/__init__.py
src/script_mananger.py
src/utils.py
src/articulation/__init__.py
src/articulation/articulation.py
src/articulation/articulation_functions.py
src/glottal/GCI.py
src/glottal/__init__.py
src/glottal/glottal.py
src/glottal/peakdetect.py
src/glottal/utils_gci.py
src/phonation/__init__.py
src/phonation/phonation.py
src/phonation/phonation_functions.py
disvoice_lurein-0.0.1.dist-info/METADATA
disvoice_lurein-0.0.1.dist-info/WHEEL
disvoice_lurein-0.0.1.dist-info/top_level.txt
disvoice_lurein-0.0.1.dist-info/RECORD
